villagers/__init__.py
villagers-0.0.1.dist-info/METADATA
villagers-0.0.1.dist-info/WHEEL
villagers-0.0.1.dist-info/RECORD
