Metadata-Version: 2.1
Name: villagers
Version: 0.0.1
Summary: Magic LLM Powered NLP Functions
Author: Hammad Saeed
Author-email: hvmmad@gmail.com
Requires-Python: >=3.10,<4.0
Classifier: Programming Language :: Python :: 3
Classifier: Programming Language :: Python :: 3.10
Classifier: Programming Language :: Python :: 3.11
Classifier: Programming Language :: Python :: 3.12
